setup.py
hatena2rst/__init__.py
hatena2rst/constants.py
hatena2rst/main.py
hatena2rst.egg-info/PKG-INFO
hatena2rst.egg-info/SOURCES.txt
hatena2rst.egg-info/dependency_links.txt
hatena2rst.egg-info/entry_points.txt
hatena2rst.egg-info/requires.txt
hatena2rst.egg-info/top_level.txt
test/test_converts.py