Metadata-Version: 1.0
Name: hatena2rst
Version: 0.0.1
Summary: Hatena archive XML converter into reST
Home-page: https://github.com/ymotongpoo/hatena2rst
Author: Yoshifumi YAMAGUCHI
Author-email: ymotongpoo at gmall.com
License: New BSD
Platform: UNKNOWN
